Metadata-Version: 2.1
Name: scrapereads
Version: 0.0.2
Summary: Scrape books and quotes on GoodReads.
Home-page: https://github.com/arthurdjn/scrape-goodreads
Author: Arthur Dujardin
Author-email: arthur.dujardin@ensg.eu
License: MIT Licence
Platform: UNKNOWN
Classifier: Development Status :: 5 - Production/Stable
Classifier: Intended Audience :: Developers
Classifier: Topic :: Software Development :: Build Tools
Classifier: License :: OSI Approved :: MIT License
Classifier: Programming Language :: Python :: 3
Classifier: Programming Language :: Python :: 3.4
Classifier: Programming Language :: Python :: 3.5
Classifier: Programming Language :: Python :: 3.6
